dbservicemanager/__init__.py
dbservicemanager/client.py
dbservicemanager/loader.py
dbservicemanager-0.1.0.dist-info/licenses/LICENSE
dbservicemanager-0.1.0.dist-info/METADATA
dbservicemanager-0.1.0.dist-info/WHEEL
dbservicemanager-0.1.0.dist-info/top_level.txt
dbservicemanager-0.1.0.dist-info/RECORD
