Metadata-Version: 2.4
Name: dbservicemanager
Version: 0.1.0
Summary: Load service environment variables from .env, cache, or remote API with full configurability
Author-email: Your Name <your.email@example.com>
License: MIT
Requires-Python: >=3.8
License-File: LICENSE
Requires-Dist: python-dotenv>=1.0.0
Requires-Dist: requests>=2.28.0
Dynamic: license-file
